{
  "url": "https://web.archive.org/web/20130427063301/http://yaplog.jp/lp-n-rena/archive/436",
  "title": "お笑い!!!",
  "date": "2008-02-22 21:10",
  "html": "<p>あ――!!おもろい!!</p><p>TKOさん!!!!!ドラえもんとか最高!!!!!!!!Σdd゜∀゜o)!!!!(笑)</p><p>妹がYouTubeで10回くらい見とるo(_ _*)o笑</p><p>あとジョイマンさんも。(●*¨$)♪</p><p>母さんの温もり～やまもりはまぐり～</p><p>ブラジルゆでじる～</p><p>…………………</p><p>ハッハッハ爆笑<br>あー面白い</p><p>あっそれと笑える漫画を見つけ出しました。</p><p>前にも言ったけど“もうかえってくれないかっ”ての!!!</p><p>めっちゃ面白いねん!!</p><p>別冊マーガレットで連載中(/*¨*)/-☆</p><p>ぜひぜひ見てください。</p><p>あと、ラブコンの作者さんが、別冊マーガレットで新連載しとる“ナナコロビン”!!これもめっちゃ面白い!!<br>あ―もう、おもくそ笑いました(笑)<br>妹が買ってて、ママとれなで妹のあとに読む順番を争っています。</p><p>漫画見ながら笑ってまうんて結構恥ずかしかった…中１までは。</p><p>今は面白いときはめっちゃ笑ってます。</p><p>!(o-ゝ-)σ)-з-)</p><p>で、笑いを堪えて堪えてしてたら堪えきれんくなって…</p><p>『うふふっ』</p><p>って不気味な笑い声が…(;゜∀゜)</p><p>だからとことん笑った方がマシだと思いました(-.-)</p><p>まあ周りから見たらどうなのかは分かりませんがね;</p><p>YouTubeで動画を見ていると右下になんか出てくるやん??あそこに“もやしもん”というアニメが…(笑)</p><p>『なにこれ――??笑』</p><p>と思い、見てみました☆<br>面白い……</p><p>なので１から全部見ました(-ε☆)<br>あれいつに放送したんでしょう…<br>れなんちのテレビじゃだめでしょうが(笑)</p><p>誰か見た事ある??}(・д・??!</p><p>なんか…すんごい換気したくなります。(-_-☆)<br>布団とかパンパンしたくなります。<br>家で寝転びたくなくなる…。</p><p>でも面白い(笑0∀0*)/:*'</p><p>…あかん。アニメの話しとったら『なんでおお振り、アニメ終わるんよ―!!!!』と頭がこんがらがる。</p><p>バッテリーもアニメすればぇえのに…とか。</p><p>皆さんはれながこれまでにブログに載せてきた</p><p>おおきく振りかぶって</p><p>バッテリー</p><p>悩殺ジャンキー</p><p>オトメン乙男</p><p>テニスの王子様</p><p>もうかえってくれないかっ</p><p>ナナコロビン</p><p>の他に面白いの見てますか??(゜゜☆)</p>",
  "content": "あ――!!おもろい!!TKOさん!!!!!ドラえもんとか最高!!!!!!!!Σdd゜∀゜o)!!!!(笑)妹がYouTubeで10回くらい見とるo(_ _*)o笑あとジョイマンさんも。(●*¨$)♪母さんの温もり～やまもりはまぐり～ブラジルゆでじる～…………………ハッハッハ爆笑あー面白いあっそれと笑える漫画を見つけ出しました。前にも言ったけど“もうかえってくれないかっ”ての!!!めっちゃ面白いねん!!別冊マーガレットで連載中(/*¨*)/-☆ぜひぜひ見てください。あと、ラブコンの作者さんが、別冊マーガレットで新連載しとる“ナナコロビン”!!これもめっちゃ面白い!!あ―もう、おもくそ笑いました(笑)妹が買ってて、ママとれなで妹のあとに読む順番を争っています。漫画見ながら笑ってまうんて結構恥ずかしかった…中１までは。今は面白いときはめっちゃ笑ってます。!(o-ゝ-)σ)-з-)で、笑いを堪えて堪えてしてたら堪えきれんくなって…『うふふっ』って不気味な笑い声が…(;゜∀゜)だからとことん笑った方がマシだと思いました(-.-)まあ周りから見たらどうなのかは分かりませんがね;YouTubeで動画を見ていると右下になんか出てくるやん??あそこに“もやしもん”というアニメが…(笑)『なにこれ――??笑』と思い、見てみました☆面白い……なので１から全部見ました(-ε☆)あれいつに放送したんでしょう…れなんちのテレビじゃだめでしょうが(笑)誰か見た事ある??}(・д・??!なんか…すんごい換気したくなります。(-_-☆)布団とかパンパンしたくなります。家で寝転びたくなくなる…。でも面白い(笑0∀0*)/:*'…あかん。アニメの話しとったら『なんでおお振り、アニメ終わるんよ―!!!!』と頭がこんがらがる。バッテリーもアニメすればぇえのに…とか。皆さんはれながこれまでにブログに載せてきたおおきく振りかぶってバッテリー悩殺ジャンキーオトメン乙男テニスの王子様もうかえってくれないかっナナコロビンの他に面白いの見てますか??(゜゜☆)",
  "assets": []
}