{
  "url": "https://web.archive.org/web/20170302044617/http://yaplog.jp/lp-n-rena/archive/955",
  "title": "いきなり",
  "date": "2013-07-22 16:09",
  "html": "<p>今夜22時からのSCHOOL OF LOCK!、GIRLS LOCKS!の四週目が始まります。<br>是非聴いてください。</p><p><img src=\"https://web.archive.org/web/20170302114902im_/http://img.yaplog.jp/img/18/pc/l/p/-/lp-n-rena/0/780.jpg\" alt=\"\"></p><p>お母さんがくれたプレゼント。<br>おとな記念のおとなかばんです。</p><p><img src=\"/collect/201307221609/781.jpg\" alt=\"\"></p><p><img src=\"https://web.archive.org/web/20170302114902im_/http://img.yaplog.jp/img/18/pc/l/p/-/lp-n-rena/0/782.jpg\" alt=\"\"></p><p><img src=\"https://web.archive.org/web/20170302114902im_/http://img.yaplog.jp/img/18/pc/l/p/-/lp-n-rena/0/783.jpg\" alt=\"\"></p><p><img src=\"https://web.archive.org/web/20170302114902im_/http://img.yaplog.jp/img/18/pc/l/p/-/lp-n-rena/0/784.jpg\" alt=\"\"></p><p><img src=\"https://web.archive.org/web/20170302114902im_/http://img.yaplog.jp/img/18/pc/l/p/-/lp-n-rena/0/785.jpg\" alt=\"\"></p><p>ギョロ。</p><p>今日の正宗パパ、素敵でしたね。<br>パパとのシーン大好き。<br>尾美さんは私の理想の男性です。えへへ</p>",
  "content": "今夜22時からのSCHOOL OF LOCK!、GIRLS LOCKS!の四週目が始まります。\n是非聴いてください。\n\n\n\n\n\n\nお母さんがくれたプレゼント。\nおとな記念のおとなかばんです。\n\n\n\n\n\n\n\n\n\n\n\n\n\n\n\n\n\nギョロ。\n\n\n今日の正宗パパ、素敵でしたね。\nパパとのシーン大好き。\n尾美さんは私の理想の男性です。えへへ",
  "assets": [
    {
      "src": "https://web.archive.org/web/20170302114902im_/http://img.yaplog.jp/img/18/pc/l/p/-/lp-n-rena/0/780.jpg",
      "alt": ""
    },
    {
      "src": "https://web.archive.org/web/20170302114902im_/http://img.yaplog.jp/img/18/pc/l/p/-/lp-n-rena/0/781.jpg",
      "alt": ""
    },
    {
      "src": "https://web.archive.org/web/20170302114902im_/http://img.yaplog.jp/img/18/pc/l/p/-/lp-n-rena/0/782.jpg",
      "alt": ""
    },
    {
      "src": "https://web.archive.org/web/20170302114902im_/http://img.yaplog.jp/img/18/pc/l/p/-/lp-n-rena/0/783.jpg",
      "alt": ""
    },
    {
      "src": "https://web.archive.org/web/20170302114902im_/http://img.yaplog.jp/img/18/pc/l/p/-/lp-n-rena/0/784.jpg",
      "alt": ""
    },
    {
      "src": "https://web.archive.org/web/20170302114902im_/http://img.yaplog.jp/img/18/pc/l/p/-/lp-n-rena/0/785.jpg",
      "alt": ""
    }
  ]
}
