{
  "url": "https://web.archive.org/web/20130904224557/http://yaplog.jp/lp-n-rena/archive/332",
  "title": "準備▲◎",
  "date": "2008-09-11 18:25",
  "html": "<p><img src=\"/collect/200809111825/10091744289_s.jpg\" alt=\"080906_0815~01.jpg\"></p><p>予行演習でした◇</p><p>◎◎◎◎◎<br>話しかけてくるのは、おじいちゃんやおばあちゃんです(´&lt;｀鯖)<br>◎◎◎◎◎</p><p>今日予行演習でした</p><p>暑い、熱い、厚い</p><p>日差しが、顔が、日焼け止めが</p><p>日焼け止め7、8回塗った(肌・&gt;・)</p><p>とりあえず、１組連合勝利!!<br>嬉し―!!</p><p>この勢いで本番も勝つ!!優勝!!</p><p>重タイヤと一致団結が一番楽しい。</p><p>重タイヤは、でっかいタイヤをひっぱりあいをします。１組VS２組で。</p><p>一致団結は、何人何脚って感じでリレーをします。これも１組VS２組で。</p><p>楽しい◇</p><p>よし頑張る▽▲</p>",
  "content": "予行演習でした◇◎◎◎◎◎話しかけてくるのは、おじいちゃんやおばあちゃんです(´<｀鯖)◎◎◎◎◎今日予行演習でした暑い、熱い、厚い日差しが、顔が、日焼け止めが日焼け止め7、8回塗った(肌・>・)とりあえず、１組連合勝利!!嬉し―!!この勢いで本番も勝つ!!優勝!!重タイヤと一致団結が一番楽しい。重タイヤは、でっかいタイヤをひっぱりあいをします。１組VS２組で。一致団結は、何人何脚って感じでリレーをします。これも１組VS２組で。楽しい◇よし頑張る▽▲",
  "assets": [
    {
      "src": "https://web.archive.org/web/20130904225854im_/http://stat.ameba.jp/user_images/07/be/10091744289_s.jpg",
      "alt": "080906_0815~01.jpg"
    }
  ]
}
