{
  "url": "https://web.archive.org/web/20170302102602/http://yaplog.jp/lp-n-rena/archive/724",
  "title": "再会ボトル",
  "date": "2011-10-05 22:02",
  "html": "<p><img src=\"/collect/201110052202/350.jpg\" alt=\"\"></p><p>今日の服です。</p><p>新しいカーデ。ボルドー。</p><p>ポケットがでかい。</p><p>そういえば小学校の時の運動会、全校生徒で10～12班とかに分かれてやってたんですが、私はたぶん8班で、班の色がボルドーだった。</p><p>………いや、ただのえんじ色だった。</p><p>***</p><p>A「地デジ化が済んだからってなんだよ。」</p><p>B「ドラマもアニメも綺麗に見れるし。」</p><p>A「…へ、へぇー…そーなん…へぇー…。」</p><p>B「いや、それよりなにより新しい電波になるのってなんかワクワクするじゃないか!!!」</p><p>今日はよく分かんない日。</p><p><img src=\"/collect/201110052202/351.jpg\" alt=\"\"></p>",
  "content": "今日の服です。\n\n新しいカーデ。ボルドー。\n\nポケットがでかい。\n\nそういえば小学校の時の運動会、全校生徒で10～12班とかに分かれてやってたんですが、私はたぶん8班で、班の色がボルドーだった。\n\n\n\n………いや、ただのえんじ色だった。\n\n\n\n***\n\n\n\nA「地デジ化が済んだからってなんだよ。」\n\nB「ドラマもアニメも綺麗に見れるし。」\n\nA「…へ、へぇー…そーなん…へぇー…。」\n\nB「いや、それよりなにより新しい電波になるのってなんかワクワクするじゃないか!!!」\n\n\n\n\n今日はよく分かんない日。",
  "assets": [
    {
      "src": "https://web.archive.org/web/20170302112822im_/http://img.yaplog.jp/img/11/pc/l/p/-/lp-n-rena/0/350.jpg",
      "alt": ""
    },
    {
      "src": "https://web.archive.org/web/20170302112822im_/http://img.yaplog.jp/img/11/pc/l/p/-/lp-n-rena/0/351.jpg",
      "alt": ""
    }
  ]
}
