{
  "url": "https://web.archive.org/web/20170302041657/http://yaplog.jp/lp-n-rena/archive/1115",
  "title": "に！",
  "date": "2015-06-30 18:47",
  "html": "<p>そういえばこないだ道を聞かれて、初めてしっかりと答えられました！<br>東京に来て初めて、人に道を教える事が出来ました。嬉しい。</p><p>海月姫Blu-ray&amp;DVD;発売まであと2日。</p><p><img src=\"/collect/201506301847/1229.png\" alt=\"\"></p><p>部活帰りみたい！</p><p>それではまた。</p><p>♪</p>",
  "content": "そういえばこないだ道を聞かれて、初めてしっかりと答えられました！\n東京に来て初めて、人に道を教える事が出来ました。嬉しい。\n\n海月姫Blu-ray&DVD;発売まであと2日。\n\n\n部活帰りみたい！\n\nそれではまた。\n\n\n\n\n♪",
  "assets": [
    {
      "src": "https://web.archive.org/web/20170302115854im_/http://img.yaplog.jp/img/18/pc/l/p/-/lp-n-rena/1/1229.png",
      "alt": ""
    }
  ]
}
