{
  "url": "https://web.archive.org/web/20130705072732/http://yaplog.jp/lp-n-rena/archive/466",
  "title": "受験生か!",
  "date": "2008-01-17 11:36",
  "html": "<p><img src=\"/collect/200801171136/10044615553_s.jpg\" alt=\"\"></p><p>いい感じで朝日が撮れた(●'`●)ノ*:☆.o</p><p>可愛いな??♪</p><p>今日はお仕事なので学校休みます。<br>明日も学校休みます。</p><p>ワーイ(●*&gt;∀&lt;艸)</p><p>と前までのれなならはしゃいでました…(o-ゝ-)σ)-з-)</p><p>でもこの頃気付いた事☆</p><p>勉強せな!!!!;;(・_・;)</p><p>れなはもうすぐ受験生…</p><p>成績表が返ってきました。</p><p>５位上がっても全然悪い(§'Д゜艸)</p><p>こりゃこの２日間で“あほ”になってまう…(°□°;)</p><p>と思いながらもお仕事があってワクワクしてますε=(ノ*・∀)ノ</p>",
  "content": "いい感じで朝日が撮れた(●'`●)ノ*:☆.o\n\n\n\n可愛いな??♪\n\n今日はお仕事なので学校休みます。\n明日も学校休みます。\n\n\n\n\nワーイ(●*>∀<艸)\n\n\n\n\n\n\n\n\n\n\nと前までのれなならはしゃいでました…(o-ゝ-)σ)-з-)\n\n\n\nでもこの頃気付いた事☆\n\n\n勉強せな!!!!;;(・_・;)\n\n\n\n\n\nれなはもうすぐ受験生…\n\n成績表が返ってきました。\n\n\n\n５位上がっても全然悪い(§'Д゜艸)\n\nこりゃこの２日間で“あほ”になってまう…(°□°;)\n\n\n\n\n\n\n\n\n\nと思いながらもお仕事があってワクワクしてますε=(ノ*・∀)ノ",
  "assets": [
    {
      "src": "https://web.archive.org/web/20130703044231im_/http://stat.ameba.jp/user_images/0e/b9/10044615553_s.jpg"
    }
  ]
}
