{
  "url": "https://web.archive.org/web/20130705013403/http://yaplog.jp/lp-n-rena/archive/669",
  "title": "☆★赤い物ばッか(☆o☆)★☆",
  "date": "2007-04-06 20:25",
  "html": "<p>やッほォォ!!今日も楽しい♪*。(笑)<br>れなの持っている物で見て思ったコト!!<br>赤いの多!!!!(∞xωＱ艸)☆.゜+。<br>アクセもバックも赤や(艸□Ｑ∞)今年買ったダウンもキャリーバッグも小物入れも赤いです★☆笑</p><p>緑もかわいいょね★☆今いっぱい出てきとって嬉しい↑↑(*0∀o艸)ヶド全然もってない(*p∩`。)<br>あとショッキングピンクと白もォ↑↑きてます(☆o☆)かわいい♪♪*。<br>みんなゎ何色がすき？！★⌒(・Pq'v`*)</p><p>ＱＡ★→☆→今欲しいものヮ…あんまりないなぁ～～!!<br>愛がこもってればなんでもいいです☆★↑↑<br>文章だけでも嬉しい★</p><p><img src=\"/collect/200704062025/10019070230_s.jpg\" alt=\"\"></p>",
  "content": "やッほォォ!!今日も楽しい♪*。(笑)\nれなの持っている物で見て思ったコト!!\n赤いの多!!!!(∞xωＱ艸)☆.゜+。\nアクセもバックも赤や(艸□Ｑ∞)今年買ったダウンもキャリーバッグも小物入れも赤いです★☆笑\n\n緑もかわいいょね★☆今いっぱい出てきとって嬉しい↑↑(*0∀o艸)ヶド全然もってない(*p∩`。)\nあとショッキングピンクと白もォ↑↑きてます(☆o☆)かわいい♪♪*。\nみんなゎ何色がすき？！★⌒(・Pq'v`*)\n\nＱＡ★→☆→今欲しいものヮ…あんまりないなぁ～～!!\n愛がこもってればなんでもいいです☆★↑↑\n文章だけでも嬉しい★",
  "assets": [
    {
      "src": "https://web.archive.org/web/20130705072944im_/http://stat.ameba.jp/user_images/36/10/10019070230_s.jpg"
    }
  ]
}
