{
  "url": "https://web.archive.org/web/20170302111216/http://yaplog.jp/lp-n-rena/archive/943",
  "title": "一粒。",
  "date": "2013-06-25 14:37",
  "html": "<p>東京編始まりました。<br>みなさん、どうでしたか？</p><p>色んな試練がアキを待っていますが、<br>(特にパパに恋人出現がショックです。)<br>それでも、あきちゃん、海に飛び込むつもりで、お馬鹿で突っ走りますから、<br>あきちゃんをどうか、暖かく応援してください。<br>宜しくお願いします。</p><p>あと、スクールオブロック能年ロックス今月も始まりました。是非、聞いてください。</p><p><img src=\"/collect/201306251437/747.jpg\" alt=\"\"></p><p>ハムを食べてるのは、ある日の朝御飯。</p>",
  "content": "東京編始まりました。\nみなさん、どうでしたか？\n\n色んな試練がアキを待っていますが、\n(特にパパに恋人出現がショックです。)\nそれでも、あきちゃん、海に飛び込むつもりで、お馬鹿で突っ走りますから、\nあきちゃんをどうか、暖かく応援してください。\n宜しくお願いします。\n\n\nあと、スクールオブロック能年ロックス今月も始まりました。是非、聞いてください。\n\n\n\n\nハムを食べてるのは、ある日の朝御飯。",
  "assets": [
    {
      "src": "https://web.archive.org/web/20170302063403im_/http://img.yaplog.jp/img/18/pc/l/p/-/lp-n-rena/0/747.jpg",
      "alt": ""
    }
  ]
}
