{
  "url": "https://web.archive.org/web/20130503034755/http://yaplog.jp/lp-n-rena/archive/296",
  "title": "メリークリスマス…",
  "date": "2008-12-25 21:24",
  "html": "<p><img src=\"/collect/200812252124/10123348759_s.jpg\" alt=\"能年 玲奈オフィシャルブログ-081225_2120~01_Ed.JPG\"></p><p>ヘッヘヘーイ！！！</p><p>メリークリスマス.....</p><p>(・・)</p><p>まっ頑張ったよな?!</p><p>テスト....</p><p>前より上がってますように....</p><p>★★★</p><p>まだ21日の興奮が冷めません....ふとした拍子に『うふふふふ―』となってしまう(;_;)</p><p>もう一度DVDで見ているて、れなが笑いくるっていると、<br>妹に『黙れ』と言われました(°°)</p><p>妹コワイわ。<br>掃除やなんじゃうるさいし…<br>そんな細かいとこ普段気にせんとこやんか！<br>自分がやる気になったときだけ巻き込むんですよ(°°;)！なんなんだい奴は…</p><p>…あ、こんなん書いたらまた後でどつかれるかも(°°;)</p><p>やっぱコワイわ。</p><p>ちくしょう！</p><p>尻にしかれるお姉ちゃん…</p><p>頑張ります！</p><p>好きな歌手って、バンドとかじゃなくてですかね？(・・)</p><p>って…クリスマスやのにぃ…ん</p><p>姉妹の上下関係暴露して終わるとこやったわ！！！(°°;)</p><p>みなさん！！！！！</p><p>メリークリスマス！！！！！！！</p><p>えっ(°д°)</p>",
  "content": "ヘッヘヘーイ！！！メリークリスマス.....(・・)まっ頑張ったよな?!テスト....前より上がってますように....★★★まだ21日の興奮が冷めません....ふとした拍子に『うふふふふ―』となってしまう(;_;)もう一度DVDで見ているて、れなが笑いくるっていると、妹に『黙れ』と言われました(°°)妹コワイわ。掃除やなんじゃうるさいし…そんな細かいとこ普段気にせんとこやんか！自分がやる気になったときだけ巻き込むんですよ(°°;)！なんなんだい奴は……あ、こんなん書いたらまた後でどつかれるかも(°°;)やっぱコワイわ。ちくしょう！尻にしかれるお姉ちゃん…頑張ります！好きな歌手って、バンドとかじゃなくてですかね？(・・)って…クリスマスやのにぃ…ん姉妹の上下関係暴露して終わるとこやったわ！！！(°°;)みなさん！！！！！メリークリスマス！！！！！！！えっ(°д°)",
  "assets": [
    {
      "src": "https://web.archive.org/web/20130503045324im_/http://stat.ameba.jp/user_images/28/80/10123348759_s.jpg",
      "alt": "能年 玲奈オフィシャルブログ-081225_2120~01_Ed.JPG"
    }
  ]
}
