{
  "url": "https://web.archive.org/web/20170302132353/http://yaplog.jp/lp-n-rena/archive/41",
  "title": "月９フジテレビ",
  "date": "2011-01-17 17:59",
  "html": "<p><img src=\"/collect/201101171759/131.gif\" alt=\"\"></p><p>大切なことはすべて君が教えてくれた</p><p>始まります。</p><p>ノイタミナも気になりますが、大君-たいきみ-(勝手に略称)、今日から毎週よろしくお願いします。(´｀*)</p><p>↑プリ機で作った、能年のデコメ</p><p>どうせ作るんやったら変な顔すれば良かった。</p><p>はい、楽しいオールバック、始まります。<br>シーユー。</p>",
  "content": "大切なことはすべて君が教えてくれた始まります。ノイタミナも気になりますが、大君-たいきみ-(勝手に略称)、今日から毎週よろしくお願いします。(´｀*)↑プリ機で作った、能年のデコメどうせ作るんやったら変な顔すれば良かった。はい、楽しいオールバック、始まります。シーユー。",
  "assets": [
    {
      "src": "https://web.archive.org/web/20170302092531im_/http://img.yaplog.jp/img/07/pc/l/p/-/lp-n-rena/0/131.gif",
      "alt": ""
    }
  ]
}
