{
  "url": "https://web.archive.org/web/20170302075744/http://yaplog.jp/lp-n-rena/archive/1047",
  "title": "ひつじ年だ。",
  "date": "2015-01-01 0:10",
  "html": "<p>明けまして、おめでとうございます。<br><img src=\"/collect/201501010010/1023.png\" alt=\"\"></p><p>新年だ。どうなるかな。<br>良い年になるよう気合い入れなきゃ。</p><p>ああ～。1年って意外と早い！<br>1年経てばぴょーん、て成長出来るのかなとか考えてましたが。<br>そんな訳なかった！<br>もっともっと頑張らなきゃ。<br>皆さんに楽しんでいただけるよう力をつけるぞ。<br>皆さんにとって、良いお年になりますように。<br><img src=\"/collect/201501010010/1024.png\" alt=\"\"></p><p>年賀状です。<br>今年もよろしくお願い致します！</p><p>♪</p>",
  "content": "明けまして、おめでとうございます。\n\n\n\n\n\n\n新年だ。どうなるかな。\n良い年になるよう気合い入れなきゃ。\n\n\nああ～。1年って意外と早い！\n1年経てばぴょーん、て成長出来るのかなとか考えてましたが。\nそんな訳なかった！\nもっともっと頑張らなきゃ。\n皆さんに楽しんでいただけるよう力をつけるぞ。\n皆さんにとって、良いお年になりますように。\n\n\n\n\n\n\n年賀状です。\n今年もよろしくお願い致します！\n\n\n\n\n\n\n\n\n\n\n♪",
  "assets": [
    {
      "src": "https://web.archive.org/web/20170302112041im_/http://img.yaplog.jp/img/18/pc/l/p/-/lp-n-rena/1/1023.png",
      "alt": ""
    },
    {
      "src": "https://web.archive.org/web/20170302112041im_/http://img.yaplog.jp/img/18/pc/l/p/-/lp-n-rena/1/1024.png",
      "alt": ""
    }
  ]
}
