{
  "url": "https://web.archive.org/web/20170302084733/http://yaplog.jp/lp-n-rena/archive/775",
  "title": "伊豆だ",
  "date": "2012-02-15 16:20",
  "html": "<p>伊豆</p><p>楽しくて写真たくさん撮ってしまいました。</p><p>ほんとに楽しかった。</p><p>そしてタビノイロの映像が暖かいから、見てると冬でもぬくぬくです。</p><p><img src=\"/collect/201202151620/416.jpg\" alt=\"\"><img src=\"/collect/201202151620/417.jpg\" alt=\"\"><img src=\"/collect/201202151620/418.jpg\" alt=\"\"><img src=\"/collect/201202151620/419.jpg\" alt=\"\"><img src=\"/collect/201202151620/420.jpg\" alt=\"\"></p>",
  "content": "伊豆 \n\n楽しくて写真たくさん撮ってしまいました。 \n\n\nほんとに楽しかった。 \n\n\n\n\nそしてタビノイロの映像が暖かいから、見てると冬でもぬくぬくです。",
  "assets": [
    {
      "src": "https://web.archive.org/web/20170302105305im_/http://img.yaplog.jp/img/14/pc/l/p/-/lp-n-rena/0/416.jpg",
      "alt": ""
    },
    {
      "src": "https://web.archive.org/web/20170302105305im_/http://img.yaplog.jp/img/14/pc/l/p/-/lp-n-rena/0/417.jpg",
      "alt": ""
    },
    {
      "src": "https://web.archive.org/web/20170302105305im_/http://img.yaplog.jp/img/14/pc/l/p/-/lp-n-rena/0/418.jpg",
      "alt": ""
    },
    {
      "src": "https://web.archive.org/web/20170302105305im_/http://img.yaplog.jp/img/14/pc/l/p/-/lp-n-rena/0/419.jpg",
      "alt": ""
    },
    {
      "src": "https://web.archive.org/web/20170302105305im_/http://img.yaplog.jp/img/14/pc/l/p/-/lp-n-rena/0/420.jpg",
      "alt": ""
    }
  ]
}
