{
  "url": "https://web.archive.org/web/20170302060118/http://yaplog.jp/lp-n-rena/archive/707",
  "title": "つまんない色",
  "date": "2011-08-05 20:00",
  "html": "<p><img src=\"https://web.archive.org/web/20170302131659im_/http://img.yaplog.jp/img/09/pc/l/p/-/lp-n-rena/0/325.jpg\" alt=\"\"></p><p>昨日、この絵に色をつけよう、と思って描いてみたんですが、うまくいかなかった。</p><p>なんかあんまよくできなかったから加工してみました。</p><p>黒塗らなかったら良かったのか…？<br>思い通りにいかなかった。<br>むはー！難しい！</p><p>***</p><p>ねこ<br>→いきなり車の中に…！<br>こ、こわ……。いつのまに乗ってたんだ…。<br>路頭に迷うより飼い主がいるのはいいと思うのですが…。<br>うーむ不思議。</p><p><img src=\"/collect/201108052000/326.jpg\" alt=\"\"></p><p><img src=\"https://web.archive.org/web/20170302131659im_/http://img.yaplog.jp/img/09/pc/l/p/-/lp-n-rena/0/327.jpg\" alt=\"\"></p>",
  "content": "昨日、この絵に色をつけよう、と思って描いてみたんですが、うまくいかなかった。\n\n\nなんかあんまよくできなかったから加工してみました。\n\n\n黒塗らなかったら良かったのか…？\n思い通りにいかなかった。\nむはー！難しい！\n\n\n\n\n***\n\n\n\nねこ\n→いきなり車の中に…！\nこ、こわ……。いつのまに乗ってたんだ…。\n路頭に迷うより飼い主がいるのはいいと思うのですが…。\nうーむ不思議。",
  "assets": [
    {
      "src": "https://web.archive.org/web/20170302131659im_/http://img.yaplog.jp/img/09/pc/l/p/-/lp-n-rena/0/325.jpg",
      "alt": ""
    },
    {
      "src": "https://web.archive.org/web/20170302131659im_/http://img.yaplog.jp/img/09/pc/l/p/-/lp-n-rena/0/326.jpg",
      "alt": ""
    },
    {
      "src": "https://web.archive.org/web/20170302131659im_/http://img.yaplog.jp/img/09/pc/l/p/-/lp-n-rena/0/327.jpg",
      "alt": ""
    }
  ]
}
