{
  "url": "https://web.archive.org/web/20130706044507/http://yaplog.jp/lp-n-rena/archive/633",
  "title": "プロポーズ大作戦☆",
  "date": "2007-06-11 22:44",
  "html": "<p><img src=\"/collect/200706112244/10023514672_s.jpg\" alt=\"070611_2228~0001.jpg\"></p><p>今日ヮプロポーズ大作戦やったね(●&gt;н艸*)<br>なんかくっつくか分からんなってきた！(☆o☆)<br>あ～はょ先みたいし(艸□`∞)<br>てヵ桑田佳祐さん動き個性的じゃない？(笑;)</p><p>てヵれなが間違えたのに皆様のコメントで励まされたょ…ライアーゲームの件。<br>ありがとうございます！(*0∀o艸)<br>楽しみな気持ちでコメみてます♪+。(●&gt;н艸*)みんなどんなんかいとんやろォ？って★</p><p>。.+お返事↑↑+.゜<br>★肌⇒石けんで洗顔♪+.゜石けんにゎ余計な成分入ってないヵラいぃらしい！(pq'ц`∞)<br>皮膚科の先生がいってた☆↑↑(*0∀o艸)<br>☆好きな色⇒赤,黒,白のトランプカラー♪(*◎'U`pq)+゜とショッキングピンク！緑もすき！(●&gt;н艸*)<br>青と白のボーダーも好き(●*¨)b+ ゜★</p><p>★成績⇒え～それゎ言えません！(笑);;微妙ですので…みんなが驚くような点数になったらお知らせする♪+.゜！★⌒(・Pq'v`*)</p><p>☆生徒諸君⇒見てますょ～～(*0∀o艸)れいちゃん出てるしね☆興味わいた(笑)(☆o☆)れいちゃん感じちがいょな！役柄やからかな(●&gt;н艸*)なんかすごいね！れいちゃん(*・V・嬉+*)<br>あと,金髪の人かっこぇえ！<br>髪の毛おろして濃い色にしたらもっといいと思う！(∞xωＱ艸)☆.゜+。<br>過去のやつのシーンでおろしとう所あったネン！その方がょかった！(*0∀o艸)</p><p>★携帯ゎauのW42Hです♪黒色！その後返してもらえました(嬉ノO凵o*)ノ.+゜:よかった☆</p><p>☆メールの正体…イヤな事にサイトからのメルマガだったのです！(怒`0ロ0#)ooO最悪～～;;</p><p>★オーディションへの渇！<br>『思ッた事ゎすぐに行動に移すこと！』<br>一生懸命で真剣な思いならばそれを突き通すこと！<br>後悔すると思うんやったらジャンジャン送ろ↑↑もちお母さんに分かってもらってね☆お母さんもきっと分かってくれるで！(*0∀o艸)オーディションに参加する子達↑！ファイト！応援してます♪</p><p>☆ライアーゲームの展開⇒れな前の回見てなくて友達に教えてもらっただヶなんやけど…<br>れなゎとにかくどうやってお金を運んでいるかを知りたい！(●&gt;н艸*)チビキノコすごいなぁ！意外と;;<br>白い髪の毛のやつも気になる…</p><p>それでゎまたね($*・Д・+。)†*。.♪</p>",
  "content": "今日ヮプロポーズ大作戦やったね(●>н艸*)なんかくっつくか分からんなってきた！(☆o☆)あ～はょ先みたいし(艸□`∞)てヵ桑田佳祐さん動き個性的じゃない？(笑;)てヵれなが間違えたのに皆様のコメントで励まされたょ…ライアーゲームの件。ありがとうございます！(*0∀o艸)楽しみな気持ちでコメみてます♪+。(●>н艸*)みんなどんなんかいとんやろォ？って★。.+お返事↑↑+.゜★肌⇒石けんで洗顔♪+.゜石けんにゎ余計な成分入ってないヵラいぃらしい！(pq'ц`∞)皮膚科の先生がいってた☆↑↑(*0∀o艸)☆好きな色⇒赤,黒,白のトランプカラー♪(*◎'U`pq)+゜とショッキングピンク！緑もすき！(●>н艸*)青と白のボーダーも好き(●*¨)b+ ゜★★成績⇒え～それゎ言えません！(笑);;微妙ですので…みんなが驚くような点数になったらお知らせする♪+.゜！★⌒(・Pq'v`*)☆生徒諸君⇒見てますょ～～(*0∀o艸)れいちゃん出てるしね☆興味わいた(笑)(☆o☆)れいちゃん感じちがいょな！役柄やからかな(●>н艸*)なんかすごいね！れいちゃん(*・V・嬉+*)あと,金髪の人かっこぇえ！髪の毛おろして濃い色にしたらもっといいと思う！(∞xωＱ艸)☆.゜+。過去のやつのシーンでおろしとう所あったネン！その方がょかった！(*0∀o艸)★携帯ゎauのW42Hです♪黒色！その後返してもらえました(嬉ノO凵o*)ノ.+゜:よかった☆☆メールの正体…イヤな事にサイトからのメルマガだったのです！(怒`0ロ0#)ooO最悪～～;;★オーディションへの渇！『思ッた事ゎすぐに行動に移すこと！』一生懸命で真剣な思いならばそれを突き通すこと！後悔すると思うんやったらジャンジャン送ろ↑↑もちお母さんに分かってもらってね☆お母さんもきっと分かってくれるで！(*0∀o艸)オーディションに参加する子達↑！ファイト！応援してます♪☆ライアーゲームの展開⇒れな前の回見てなくて友達に教えてもらっただヶなんやけど…れなゎとにかくどうやってお金を運んでいるかを知りたい！(●>н艸*)チビキノコすごいなぁ！意外と;;白い髪の毛のやつも気になる…それでゎまたね($*・Д・+。)†*。.♪",
  "assets": [
    {
      "src": "https://web.archive.org/web/20130706044502im_/http://stat.ameba.jp/user_images/ce/e3/10023514672_s.jpg",
      "alt": "070611_2228~0001.jpg"
    }
  ]
}
